{
  "parent": "minecraft:recipes/root",
  "criteria": {
    "has_cyan_terracotta": {
      "trigger": "minecraft:inventory_changed",
      "conditions": {
        "items": [
          {
            "items": "minecraft:cyan_terracotta"
          }
        ]
      }
    },
    "has_the_recipe": {
      "trigger": "minecraft:recipe_unlocked",
      "conditions": {
        "recipe": "minecraft:cyan_glazed_terracotta_from_blasting"
      }
    }
  },
  "requirements": [
    [
      "has_cyan_terracotta",
      "has_the_recipe"
    ]
  ],
  "rewards": {
    "recipes": [
      "minecraft:cyan_glazed_terracotta_from_blasting"
    ]
  }
}