{
  "display": {
    "icon": {
      "item": "minecraft:gold_ingot"
    },
    "title": {
      "translate": "advancements.milestone.story.obtain_gold.title"
    },
    "description": {
      "translate": "advancements.milestone.story.obtain_gold.description"
    },
    "show_toast": true,
    "announce_to_chat": true
  },
  "parent": "milestone:story/kill_a_mob",
    "criteria": {
    "obtain_gold": {
      "trigger": "minecraft:inventory_changed",
      "conditions": {
        "items": [
          {
            "items": [
              "minecraft:gold_ingot"
            ]
          }
        ]
      }
    }
  },
  "sends_telemetry_event": true
}