{
  "parent": "item/handheld",
  "overrides": [
    {
      "model": "item/golden_sword_quartz_trim",
      "predicate": {
        "trim_type": 0.1
      }
    },
    {
      "model": "item/golden_sword_iron_trim",
      "predicate": {
        "trim_type": 0.2
      }
    },
    {
      "model": "item/golden_sword_netherite_trim",
      "predicate": {
        "trim_type": 0.3
      }
    },
    {
      "model": "item/golden_sword_redstone_trim",
      "predicate": {
        "trim_type": 0.4
      }
    },
    {
      "model": "item/golden_sword_copper_trim",
      "predicate": {
        "trim_type": 0.5
      }
    },
    {
      "model": "item/golden_sword_gold_darker_trim",
      "predicate": {
        "trim_type": 0.6
      }
    },
    {
      "model": "item/golden_sword_emerald_trim",
      "predicate": {
        "trim_type": 0.7
      }
    },
    {
      "model": "item/golden_sword_diamond_trim",
      "predicate": {
        "trim_type": 0.8
      }
    },
    {
      "model": "item/golden_sword_lapis_trim",
      "predicate": {
        "trim_type": 0.9
      }
    },
    {
      "model": "item/golden_sword_amethyst_trim",
      "predicate": {
        "trim_type": 1.0
      }
    }
  ],
  "textures": {
    "layer0": "item/golden_sword"
  }
}